onnx2pytorch/__init__.py
onnx2pytorch/constants.py
onnx2pytorch/dtypes.py
onnx2pytorch/helpers.py
onnx2pytorch/utils.py
onnx2pytorch/convert/__init__.py
onnx2pytorch/convert/attribute.py
onnx2pytorch/convert/debug.py
onnx2pytorch/convert/layer.py
onnx2pytorch/convert/model.py
onnx2pytorch/convert/operations.py
onnx2pytorch/operations/__init__.py
onnx2pytorch/operations/add.py
onnx2pytorch/operations/autopad.py
onnx2pytorch/operations/base.py
onnx2pytorch/operations/batchnorm.py
onnx2pytorch/operations/bitshift.py
onnx2pytorch/operations/cast.py
onnx2pytorch/operations/clip.py
onnx2pytorch/operations/constant.py
onnx2pytorch/operations/constantofshape.py
onnx2pytorch/operations/div.py
onnx2pytorch/operations/expand.py
onnx2pytorch/operations/flatten.py
onnx2pytorch/operations/gather.py
onnx2pytorch/operations/gathernd.py
onnx2pytorch/operations/globalaveragepool.py
onnx2pytorch/operations/gru.py
onnx2pytorch/operations/hardsigmoid.py
onnx2pytorch/operations/if_op.py
onnx2pytorch/operations/instancenorm.py
onnx2pytorch/operations/layernorm.py
onnx2pytorch/operations/loop.py
onnx2pytorch/operations/lrn.py
onnx2pytorch/operations/lstm.py
onnx2pytorch/operations/matmul.py
onnx2pytorch/operations/nonmaxsuppression.py
onnx2pytorch/operations/onehot.py
onnx2pytorch/operations/optional.py
onnx2pytorch/operations/pad.py
onnx2pytorch/operations/prelu.py
onnx2pytorch/operations/randomuniformlike.py
onnx2pytorch/operations/range.py
onnx2pytorch/operations/reducel2.py
onnx2pytorch/operations/reducemax.py
onnx2pytorch/operations/reducesum.py
onnx2pytorch/operations/reducesumsquare.py
onnx2pytorch/operations/reshape.py
onnx2pytorch/operations/resize.py
onnx2pytorch/operations/scatter.py
onnx2pytorch/operations/scatterelements.py
onnx2pytorch/operations/scatternd.py
onnx2pytorch/operations/sequenceconstruct.py
onnx2pytorch/operations/shape.py
onnx2pytorch/operations/slice.py
onnx2pytorch/operations/split.py
onnx2pytorch/operations/squeeze.py
onnx2pytorch-0.5.3.dist-info/LICENSE
onnx2pytorch-0.5.3.dist-info/METADATA
onnx2pytorch-0.5.3.dist-info/WHEEL
onnx2pytorch-0.5.3.dist-info/top_level.txt
onnx2pytorch-0.5.3.dist-info/RECORD
