Metadata-Version: 2.1
Name: onnx2pytorch
Version: 0.5.3
Summary: Library to transform onnx model to pytorch.
Home-page: https://github.com/ToriML/onnx2pytorch
Author: Talmaj Marinc
License: apache-2.0
Classifier: Programming Language :: Python :: 3
Classifier: License :: OSI Approved :: Apache Software License
Classifier: Operating System :: OS Independent
Requires-Python: >=3.6
License-File: LICENSE
Requires-Dist: torch>=1.4.0
Requires-Dist: onnx>=1.6.0
Requires-Dist: torchvision>=0.9.0
